{
  "size": {
    "2": {
      "description": null,
      "value": 2,
      "type": "dimension",
      "extensions": {
        "org.lukasoppermann.figmaDesignTokens": {
          "exportKey": "size"
        }
      }
    },
    "4": {
      "description": null,
      "value": 4,
      "type": "dimension",
      "extensions": {
        "org.lukasoppermann.figmaDesignTokens": {
          "exportKey": "size"
        }
      }
    },
    "8": {
      "description": null,
      "value": 8,
      "type": "dimension",
      "extensions": {
        "org.lukasoppermann.figmaDesignTokens": {
          "exportKey": "size"
        }
      }
    },
    "12": {
      "description": null,
      "value": 12,
      "type": "dimension",
      "extensions": {
        "org.lukasoppermann.figmaDesignTokens": {
          "exportKey": "size"
        }
      }
    },
    "16": {
      "description": null,
      "value": 16,
      "type": "dimension",
      "extensions": {
        "org.lukasoppermann.figmaDesignTokens": {
          "exportKey": "size"
        }
      }
    },
    "24": {
      "description": null,
      "value": 24,
      "type": "dimension",
      "extensions": {
        "org.lukasoppermann.figmaDesignTokens": {
          "exportKey": "size"
        }
      }
    },
    "32": {
      "description": null,
      "value": 32,
      "type": "dimension",
      "extensions": {
        "org.lukasoppermann.figmaDesignTokens": {
          "exportKey": "size"
        }
      }
    },
    "40": {
      "description": null,
      "value": 40,
      "type": "dimension",
      "extensions": {
        "org.lukasoppermann.figmaDesignTokens": {
          "exportKey": "size"
        }
      }
    },
    "48": {
      "description": null,
      "value": 48,
      "type": "dimension",
      "extensions": {
        "org.lukasoppermann.figmaDesignTokens": {
          "exportKey": "size"
        }
      }
    },
    "64": {
      "description": null,
      "value": 64,
      "type": "dimension",
      "extensions": {
        "org.lukasoppermann.figmaDesignTokens": {
          "exportKey": "size"
        }
      }
    },
    "80": {
      "description": null,
      "value": 80,
      "type": "dimension",
      "extensions": {
        "org.lukasoppermann.figmaDesignTokens": {
          "exportKey": "size"
        }
      }
    }
  },
  "color": {
    "palette": {
      "black": {
        "description": "",
        "type": "color",
        "value": "#000000ff",
        "blendMode": "normal",
        "extensions": {
          "org.lukasoppermann.figmaDesignTokens": {
            "styleId": "S:a29a7ee45574aab0e79c1bd9d612c5b7d964ead5,",
            "exportKey": "color"
          }
        }
      },
      "white": {
        "description": "",
        "type": "color",
        "value": "#ffffffff",
        "blendMode": "normal",
        "extensions": {
          "org.lukasoppermann.figmaDesignTokens": {
            "styleId": "S:2a80f2b6c8731891b44641b5a926794388daf56b,",
            "exportKey": "color"
          }
        }
      },
      "wag red": {
        "description": "",
        "type": "color",
        "value": "#e62600ff",
        "blendMode": "normal",
        "extensions": {
          "org.lukasoppermann.figmaDesignTokens": {
            "styleId": "S:4f5d77d83ea90a57a6fe4fa50b823daa73db74bd,",
            "exportKey": "color"
          }
        }
      },
      "navy": {
        "description": "",
        "type": "color",
        "value": "#323264ff",
        "blendMode": "normal",
        "extensions": {
          "org.lukasoppermann.figmaDesignTokens": {
            "styleId": "S:9ce1791364487aaa303db346fa15b09315f82b1c,",
            "exportKey": "color"
          }
        }
      },
      "cream": {
        "description": "",
        "type": "color",
        "value": "#f5f5f0ff",
        "blendMode": "normal",
        "extensions": {
          "org.lukasoppermann.figmaDesignTokens": {
            "styleId": "S:f8cce3006288bffb90d7d0c20c001e316001b014,",
            "exportKey": "color"
          }
        }
      },
      "sky": {
        "description": "",
        "type": "color",
        "value": "#c2e8ffff",
        "blendMode": "normal",
        "extensions": {
          "org.lukasoppermann.figmaDesignTokens": {
            "styleId": "S:5df298b8b90c5eb25d0ba7e54282f14a2168a1fc,",
            "exportKey": "color"
          }
        }
      },
      "denim": {
        "description": "",
        "type": "color",
        "value": "#284b9bff",
        "blendMode": "normal",
        "extensions": {
          "org.lukasoppermann.figmaDesignTokens": {
            "styleId": "S:fb98a3d87550730436044e97d6236dc3e43d64d9,",
            "exportKey": "color"
          }
        }
      },
      "teal": {
        "description": "",
        "type": "color",
        "value": "#0082aaff",
        "blendMode": "normal",
        "extensions": {
          "org.lukasoppermann.figmaDesignTokens": {
            "styleId": "S:6feb6f514f3cb82b1ac47b1fbe9e297aebee7bbc,",
            "exportKey": "color"
          }
        }
      },
      "gray 100": {
        "description": "",
        "type": "color",
        "value": "#d9dadaff",
        "blendMode": "normal",
        "extensions": {
          "org.lukasoppermann.figmaDesignTokens": {
            "styleId": "S:c28848d7777cf2737b5cf0d15cc271a325317e19,",
            "exportKey": "color"
          }
        }
      },
      "gray 200": {
        "description": "",
        "type": "color",
        "value": "#989090ff",
        "blendMode": "normal",
        "extensions": {
          "org.lukasoppermann.figmaDesignTokens": {
            "styleId": "S:93433e078894a88c137bcd67a506334d10e2bff3,",
            "exportKey": "color"
          }
        }
      },
      "gray 300": {
        "description": "",
        "type": "color",
        "value": "#707575ff",
        "blendMode": "normal",
        "extensions": {
          "org.lukasoppermann.figmaDesignTokens": {
            "styleId": "S:e463d0177c884e1dbcad00ea7a6a4a3b643ca30b,",
            "exportKey": "color"
          }
        }
      },
      "gray 400": {
        "description": "",
        "type": "color",
        "value": "#0a1414ff",
        "blendMode": "normal",
        "extensions": {
          "org.lukasoppermann.figmaDesignTokens": {
            "styleId": "S:6f65af91971b77370e4d55b8eac51e6ce8a5d8a0,",
            "exportKey": "color"
          }
        }
      },
      "sky blue tint": {
        "description": "",
        "type": "color",
        "value": "#a7dee9ff",
        "blendMode": "normal",
        "extensions": {
          "org.lukasoppermann.figmaDesignTokens": {
            "styleId": "S:f26639b02c82adc80ff7c70bfee947067c1435d0,",
            "exportKey": "color"
          }
        }
      }
    },
    "background": {
      "primary.light": {
        "description": "",
        "type": "color",
        "value": "#ffffffff",
        "blendMode": "normal",
        "extensions": {
          "org.lukasoppermann.figmaDesignTokens": {
            "styleId": "S:185b19f663540ceec385e6e670185ce42f51ac8e,",
            "exportKey": "color"
          }
        }
      },
      "secondary.light": {
        "description": "",
        "type": "color",
        "value": "#f5f5f0ff",
        "blendMode": "normal",
        "extensions": {
          "org.lukasoppermann.figmaDesignTokens": {
            "styleId": "S:44df9454044685f0f07348825faae6107fa0cedc,",
            "exportKey": "color"
          }
        }
      },
      "tertiary.light": {
        "description": "",
        "type": "color",
        "value": "#c2e8ffff",
        "blendMode": "normal",
        "extensions": {
          "org.lukasoppermann.figmaDesignTokens": {
            "styleId": "S:4b12de4a0f2cc1935c504381795a2c0ec403b0cb,",
            "exportKey": "color"
          }
        }
      },
      "primary.dark": {
        "description": "",
        "type": "color",
        "value": "#323264ff",
        "blendMode": "normal",
        "extensions": {
          "org.lukasoppermann.figmaDesignTokens": {
            "styleId": "S:d2f11af97c3f53fc77fd50ccf78902bd1240cd5c,",
            "exportKey": "color"
          }
        }
      },
      "secondary.dark": {
        "description": "",
        "type": "color",
        "value": "#284b9bff",
        "blendMode": "normal",
        "extensions": {
          "org.lukasoppermann.figmaDesignTokens": {
            "styleId": "S:106f30e187bd8770130d6afe80e419fd53af9090,",
            "exportKey": "color"
          }
        }
      }
    },
    "elements": {
      "primary.onlight": {
        "description": "",
        "type": "color",
        "value": "#0a1414ff",
        "blendMode": "normal",
        "extensions": {
          "org.lukasoppermann.figmaDesignTokens": {
            "styleId": "S:5ad2e6d562ddb4504e4dbbc2926a65ed35789a13,",
            "exportKey": "color"
          }
        }
      },
      "secondary.onlight": {
        "description": "",
        "type": "color",
        "value": "#707575ff",
        "blendMode": "normal",
        "extensions": {
          "org.lukasoppermann.figmaDesignTokens": {
            "styleId": "S:4dfc47f402d942db7335c9c4cce19be69fcbac1b,",
            "exportKey": "color"
          }
        }
      },
      "tertiary.onlight": {
        "description": "",
        "type": "color",
        "value": "#989090ff",
        "blendMode": "normal",
        "extensions": {
          "org.lukasoppermann.figmaDesignTokens": {
            "styleId": "S:d1388b50a95be8920b1d76b928863bd95a3803ec,",
            "exportKey": "color"
          }
        }
      },
      "primary.ondark": {
        "description": "",
        "type": "color",
        "value": "#ffffffff",
        "blendMode": "normal",
        "extensions": {
          "org.lukasoppermann.figmaDesignTokens": {
            "styleId": "S:c2f38e2e27cbf18bb463632ab16dea33f67094ab,",
            "exportKey": "color"
          }
        }
      },
      "primary.highlight": {
        "description": "",
        "type": "color",
        "value": "#284b9bff",
        "blendMode": "normal",
        "extensions": {
          "org.lukasoppermann.figmaDesignTokens": {
            "styleId": "S:bca305cec92c7a7cb692b2c962b0354942de268f,",
            "exportKey": "color"
          }
        }
      },
      "secondary.highlight": {
        "description": "",
        "type": "color",
        "value": "#323264ff",
        "blendMode": "normal",
        "extensions": {
          "org.lukasoppermann.figmaDesignTokens": {
            "styleId": "S:a4858291fc43de47322d67a28e571f743cca2709,",
            "exportKey": "color"
          }
        }
      },
      "disabled.onlight": {
        "description": "",
        "type": "color",
        "value": "#d9dadaff",
        "blendMode": "normal",
        "extensions": {
          "org.lukasoppermann.figmaDesignTokens": {
            "styleId": "S:e3cfc47b42ab1fb8e7c180ee44e4fac4e813e85a,",
            "exportKey": "color"
          }
        }
      }
    },
    "interactive": {
      "active.primary.ondark": {
        "description": "",
        "type": "color",
        "value": "#ffffffff",
        "blendMode": "normal",
        "extensions": {
          "org.lukasoppermann.figmaDesignTokens": {
            "styleId": "S:227ca96f176221cba038b98a3ace93b61646f3d0,",
            "exportKey": "color"
          }
        }
      },
      "active.primary.onlight": {
        "description": "",
        "type": "color",
        "value": "#284b9bff",
        "blendMode": "normal",
        "extensions": {
          "org.lukasoppermann.figmaDesignTokens": {
            "styleId": "S:8fa6deed0892e3240437c734752d2015efffbe91,",
            "exportKey": "color"
          }
        }
      },
      "active.secondary.onlight": {
        "description": "",
        "type": "color",
        "value": "#323264ff",
        "blendMode": "normal",
        "extensions": {
          "org.lukasoppermann.figmaDesignTokens": {
            "styleId": "S:f2e343e40d7b687c369bdc71eb6bace35b63ee38,",
            "exportKey": "color"
          }
        }
      },
      "active.tertiary.onlight": {
        "description": "",
        "type": "color",
        "value": "#c2e8ffff",
        "blendMode": "normal",
        "extensions": {
          "org.lukasoppermann.figmaDesignTokens": {
            "styleId": "S:3409269cde6a2ff2f0622c85902ae5bc5cea205f,",
            "exportKey": "color"
          }
        }
      },
      "hover.tertiary.onlight": {
        "description": "",
        "type": "color",
        "value": "#a7dee9ff",
        "blendMode": "normal",
        "extensions": {
          "org.lukasoppermann.figmaDesignTokens": {
            "styleId": "S:991ce15039ee4996d0d812a91dfd81c5e87de6db,",
            "exportKey": "color"
          }
        }
      },
      "disabled.onlight": {
        "description": "",
        "type": "color",
        "value": "#d9dadaff",
        "blendMode": "normal",
        "extensions": {
          "org.lukasoppermann.figmaDesignTokens": {
            "styleId": "S:aefd8c60d434aec7a7d74e0c2d4f4f09160d8223,",
            "exportKey": "color"
          }
        }
      }
    }
  },
  "typography": {
    "desktop": {
      "display": {
        "xsmall bold": {
          "fontSize": {
            "type": "dimension",
            "value": 36
          },
          "textDecoration": {
            "type": "string",
            "value": "none"
          },
          "fontFamily": {
            "type": "string",
            "value": "Source Sans Pro"
          },
          "fontWeight": {
            "type": "number",
            "value": 700
          },
          "fontStyle": {
            "type": "string",
            "value": "normal"
          },
          "fontStretch": {
            "type": "string",
            "value": "normal"
          },
          "letterSpacing": {
            "type": "dimension",
            "value": 0
          },
          "lineHeight": {
            "type": "dimension",
            "value": 40
          },
          "paragraphIndent": {
            "type": "dimension",
            "value": 0
          },
          "paragraphSpacing": {
            "type": "dimension",
            "value": 0
          },
          "textCase": {
            "type": "string",
            "value": "none"
          }
        },
        "xsmall regular": {
          "fontSize": {
            "type": "dimension",
            "value": 36
          },
          "textDecoration": {
            "type": "string",
            "value": "none"
          },
          "fontFamily": {
            "type": "string",
            "value": "Source Sans Pro"
          },
          "fontWeight": {
            "type": "number",
            "value": 400
          },
          "fontStyle": {
            "type": "string",
            "value": "normal"
          },
          "fontStretch": {
            "type": "string",
            "value": "normal"
          },
          "letterSpacing": {
            "type": "dimension",
            "value": 0
          },
          "lineHeight": {
            "type": "dimension",
            "value": 40
          },
          "paragraphIndent": {
            "type": "dimension",
            "value": 0
          },
          "paragraphSpacing": {
            "type": "dimension",
            "value": 0
          },
          "textCase": {
            "type": "string",
            "value": "none"
          }
        }
      },
      "title": {
        "large bold": {
          "fontSize": {
            "type": "dimension",
            "value": 28
          },
          "textDecoration": {
            "type": "string",
            "value": "none"
          },
          "fontFamily": {
            "type": "string",
            "value": "Source Sans Pro"
          },
          "fontWeight": {
            "type": "number",
            "value": 700
          },
          "fontStyle": {
            "type": "string",
            "value": "normal"
          },
          "fontStretch": {
            "type": "string",
            "value": "normal"
          },
          "letterSpacing": {
            "type": "dimension",
            "value": 0
          },
          "lineHeight": {
            "type": "dimension",
            "value": 34
          },
          "paragraphIndent": {
            "type": "dimension",
            "value": 0
          },
          "paragraphSpacing": {
            "type": "dimension",
            "value": 0
          },
          "textCase": {
            "type": "string",
            "value": "none"
          }
        },
        "large regular": {
          "fontSize": {
            "type": "dimension",
            "value": 28
          },
          "textDecoration": {
            "type": "string",
            "value": "none"
          },
          "fontFamily": {
            "type": "string",
            "value": "Source Sans Pro"
          },
          "fontWeight": {
            "type": "number",
            "value": 400
          },
          "fontStyle": {
            "type": "string",
            "value": "normal"
          },
          "fontStretch": {
            "type": "string",
            "value": "normal"
          },
          "letterSpacing": {
            "type": "dimension",
            "value": 0
          },
          "lineHeight": {
            "type": "dimension",
            "value": 34
          },
          "paragraphIndent": {
            "type": "dimension",
            "value": 0
          },
          "paragraphSpacing": {
            "type": "dimension",
            "value": 0
          },
          "textCase": {
            "type": "string",
            "value": "none"
          }
        },
        "medium bold": {
          "fontSize": {
            "type": "dimension",
            "value": 22
          },
          "textDecoration": {
            "type": "string",
            "value": "none"
          },
          "fontFamily": {
            "type": "string",
            "value": "Source Sans Pro"
          },
          "fontWeight": {
            "type": "number",
            "value": 700
          },
          "fontStyle": {
            "type": "string",
            "value": "normal"
          },
          "fontStretch": {
            "type": "string",
            "value": "normal"
          },
          "letterSpacing": {
            "type": "dimension",
            "value": 0
          },
          "lineHeight": {
            "type": "dimension",
            "value": 30
          },
          "paragraphIndent": {
            "type": "dimension",
            "value": 0
          },
          "paragraphSpacing": {
            "type": "dimension",
            "value": 0
          },
          "textCase": {
            "type": "string",
            "value": "none"
          }
        },
        "medium regular": {
          "fontSize": {
            "type": "dimension",
            "value": 22
          },
          "textDecoration": {
            "type": "string",
            "value": "none"
          },
          "fontFamily": {
            "type": "string",
            "value": "Source Sans Pro"
          },
          "fontWeight": {
            "type": "number",
            "value": 400
          },
          "fontStyle": {
            "type": "string",
            "value": "normal"
          },
          "fontStretch": {
            "type": "string",
            "value": "normal"
          },
          "letterSpacing": {
            "type": "dimension",
            "value": 0
          },
          "lineHeight": {
            "type": "dimension",
            "value": 30
          },
          "paragraphIndent": {
            "type": "dimension",
            "value": 0
          },
          "paragraphSpacing": {
            "type": "dimension",
            "value": 0
          },
          "textCase": {
            "type": "string",
            "value": "none"
          }
        },
        "small bold": {
          "fontSize": {
            "type": "dimension",
            "value": 18
          },
          "textDecoration": {
            "type": "string",
            "value": "none"
          },
          "fontFamily": {
            "type": "string",
            "value": "Source Sans Pro"
          },
          "fontWeight": {
            "type": "number",
            "value": 700
          },
          "fontStyle": {
            "type": "string",
            "value": "normal"
          },
          "fontStretch": {
            "type": "string",
            "value": "normal"
          },
          "letterSpacing": {
            "type": "dimension",
            "value": 0
          },
          "lineHeight": {
            "type": "dimension",
            "value": 22
          },
          "paragraphIndent": {
            "type": "dimension",
            "value": 0
          },
          "paragraphSpacing": {
            "type": "dimension",
            "value": 0
          },
          "textCase": {
            "type": "string",
            "value": "none"
          }
        },
        "small regular": {
          "fontSize": {
            "type": "dimension",
            "value": 18
          },
          "textDecoration": {
            "type": "string",
            "value": "none"
          },
          "fontFamily": {
            "type": "string",
            "value": "Source Sans Pro"
          },
          "fontWeight": {
            "type": "number",
            "value": 400
          },
          "fontStyle": {
            "type": "string",
            "value": "normal"
          },
          "fontStretch": {
            "type": "string",
            "value": "normal"
          },
          "letterSpacing": {
            "type": "dimension",
            "value": 0
          },
          "lineHeight": {
            "type": "dimension",
            "value": 22
          },
          "paragraphIndent": {
            "type": "dimension",
            "value": 0
          },
          "paragraphSpacing": {
            "type": "dimension",
            "value": 0
          },
          "textCase": {
            "type": "string",
            "value": "none"
          }
        },
        "xsmall bold": {
          "fontSize": {
            "type": "dimension",
            "value": 16
          },
          "textDecoration": {
            "type": "string",
            "value": "none"
          },
          "fontFamily": {
            "type": "string",
            "value": "Source Sans Pro"
          },
          "fontWeight": {
            "type": "number",
            "value": 700
          },
          "fontStyle": {
            "type": "string",
            "value": "normal"
          },
          "fontStretch": {
            "type": "string",
            "value": "normal"
          },
          "letterSpacing": {
            "type": "dimension",
            "value": 0
          },
          "lineHeight": {
            "type": "dimension",
            "value": 22
          },
          "paragraphIndent": {
            "type": "dimension",
            "value": 0
          },
          "paragraphSpacing": {
            "type": "dimension",
            "value": 0
          },
          "textCase": {
            "type": "string",
            "value": "none"
          }
        },
        "xsmall regular": {
          "fontSize": {
            "type": "dimension",
            "value": 16
          },
          "textDecoration": {
            "type": "string",
            "value": "none"
          },
          "fontFamily": {
            "type": "string",
            "value": "Source Sans Pro"
          },
          "fontWeight": {
            "type": "number",
            "value": 400
          },
          "fontStyle": {
            "type": "string",
            "value": "normal"
          },
          "fontStretch": {
            "type": "string",
            "value": "normal"
          },
          "letterSpacing": {
            "type": "dimension",
            "value": 0
          },
          "lineHeight": {
            "type": "dimension",
            "value": 22
          },
          "paragraphIndent": {
            "type": "dimension",
            "value": 0
          },
          "paragraphSpacing": {
            "type": "dimension",
            "value": 0
          },
          "textCase": {
            "type": "string",
            "value": "none"
          }
        },
        "micro bold": {
          "fontSize": {
            "type": "dimension",
            "value": 14
          },
          "textDecoration": {
            "type": "string",
            "value": "none"
          },
          "fontFamily": {
            "type": "string",
            "value": "Source Sans Pro"
          },
          "fontWeight": {
            "type": "number",
            "value": 700
          },
          "fontStyle": {
            "type": "string",
            "value": "normal"
          },
          "fontStretch": {
            "type": "string",
            "value": "normal"
          },
          "letterSpacing": {
            "type": "dimension",
            "value": 0
          },
          "lineHeight": {
            "type": "dimension",
            "value": 16
          },
          "paragraphIndent": {
            "type": "dimension",
            "value": 0
          },
          "paragraphSpacing": {
            "type": "dimension",
            "value": 0
          },
          "textCase": {
            "type": "string",
            "value": "none"
          }
        },
        "micro regular": {
          "fontSize": {
            "type": "dimension",
            "value": 14
          },
          "textDecoration": {
            "type": "string",
            "value": "none"
          },
          "fontFamily": {
            "type": "string",
            "value": "Source Sans Pro"
          },
          "fontWeight": {
            "type": "number",
            "value": 400
          },
          "fontStyle": {
            "type": "string",
            "value": "normal"
          },
          "fontStretch": {
            "type": "string",
            "value": "normal"
          },
          "letterSpacing": {
            "type": "dimension",
            "value": 0
          },
          "lineHeight": {
            "type": "dimension",
            "value": 16
          },
          "paragraphIndent": {
            "type": "dimension",
            "value": 0
          },
          "paragraphSpacing": {
            "type": "dimension",
            "value": 0
          },
          "textCase": {
            "type": "string",
            "value": "none"
          }
        }
      },
      "body": {
        "large": {
          "fontSize": {
            "type": "dimension",
            "value": 18
          },
          "textDecoration": {
            "type": "string",
            "value": "none"
          },
          "fontFamily": {
            "type": "string",
            "value": "Source Sans Pro"
          },
          "fontWeight": {
            "type": "number",
            "value": 400
          },
          "fontStyle": {
            "type": "string",
            "value": "normal"
          },
          "fontStretch": {
            "type": "string",
            "value": "normal"
          },
          "letterSpacing": {
            "type": "dimension",
            "value": 0
          },
          "lineHeight": {
            "type": "dimension",
            "value": 32
          },
          "paragraphIndent": {
            "type": "dimension",
            "value": 0
          },
          "paragraphSpacing": {
            "type": "dimension",
            "value": 0
          },
          "textCase": {
            "type": "string",
            "value": "none"
          }
        },
        "medium": {
          "fontSize": {
            "type": "dimension",
            "value": 16
          },
          "textDecoration": {
            "type": "string",
            "value": "none"
          },
          "fontFamily": {
            "type": "string",
            "value": "Source Sans Pro"
          },
          "fontWeight": {
            "type": "number",
            "value": 400
          },
          "fontStyle": {
            "type": "string",
            "value": "normal"
          },
          "fontStretch": {
            "type": "string",
            "value": "normal"
          },
          "letterSpacing": {
            "type": "dimension",
            "value": 0
          },
          "lineHeight": {
            "type": "dimension",
            "value": 24
          },
          "paragraphIndent": {
            "type": "dimension",
            "value": 0
          },
          "paragraphSpacing": {
            "type": "dimension",
            "value": 0
          },
          "textCase": {
            "type": "string",
            "value": "none"
          }
        },
        "small": {
          "fontSize": {
            "type": "dimension",
            "value": 14
          },
          "textDecoration": {
            "type": "string",
            "value": "none"
          },
          "fontFamily": {
            "type": "string",
            "value": "Source Sans Pro"
          },
          "fontWeight": {
            "type": "number",
            "value": 400
          },
          "fontStyle": {
            "type": "string",
            "value": "normal"
          },
          "fontStretch": {
            "type": "string",
            "value": "normal"
          },
          "letterSpacing": {
            "type": "dimension",
            "value": 0
          },
          "lineHeight": {
            "type": "dimension",
            "value": 21
          },
          "paragraphIndent": {
            "type": "dimension",
            "value": 0
          },
          "paragraphSpacing": {
            "type": "dimension",
            "value": 0
          },
          "textCase": {
            "type": "string",
            "value": "none"
          }
        },
        "micro": {
          "fontSize": {
            "type": "dimension",
            "value": 11
          },
          "textDecoration": {
            "type": "string",
            "value": "none"
          },
          "fontFamily": {
            "type": "string",
            "value": "Source Sans Pro"
          },
          "fontWeight": {
            "type": "number",
            "value": 400
          },
          "fontStyle": {
            "type": "string",
            "value": "normal"
          },
          "fontStretch": {
            "type": "string",
            "value": "normal"
          },
          "letterSpacing": {
            "type": "dimension",
            "value": 0
          },
          "lineHeight": {
            "type": "dimension",
            "value": 14
          },
          "paragraphIndent": {
            "type": "dimension",
            "value": 0
          },
          "paragraphSpacing": {
            "type": "dimension",
            "value": 0
          },
          "textCase": {
            "type": "string",
            "value": "none"
          }
        }
      }
    },
    "mobile": {
      "display": {
        "xsmall bold": {
          "fontSize": {
            "type": "dimension",
            "value": 28
          },
          "textDecoration": {
            "type": "string",
            "value": "none"
          },
          "fontFamily": {
            "type": "string",
            "value": "Source Sans Pro"
          },
          "fontWeight": {
            "type": "number",
            "value": 700
          },
          "fontStyle": {
            "type": "string",
            "value": "normal"
          },
          "fontStretch": {
            "type": "string",
            "value": "normal"
          },
          "letterSpacing": {
            "type": "dimension",
            "value": 0
          },
          "lineHeight": {
            "type": "dimension",
            "value": 34
          },
          "paragraphIndent": {
            "type": "dimension",
            "value": 0
          },
          "paragraphSpacing": {
            "type": "dimension",
            "value": 0
          },
          "textCase": {
            "type": "string",
            "value": "none"
          }
        },
        "xsmall regular": {
          "fontSize": {
            "type": "dimension",
            "value": 28
          },
          "textDecoration": {
            "type": "string",
            "value": "none"
          },
          "fontFamily": {
            "type": "string",
            "value": "Source Sans Pro"
          },
          "fontWeight": {
            "type": "number",
            "value": 400
          },
          "fontStyle": {
            "type": "string",
            "value": "normal"
          },
          "fontStretch": {
            "type": "string",
            "value": "normal"
          },
          "letterSpacing": {
            "type": "dimension",
            "value": 0
          },
          "lineHeight": {
            "type": "dimension",
            "value": 34
          },
          "paragraphIndent": {
            "type": "dimension",
            "value": 0
          },
          "paragraphSpacing": {
            "type": "dimension",
            "value": 0
          },
          "textCase": {
            "type": "string",
            "value": "none"
          }
        }
      },
      "title": {
        "medium bold": {
          "fontSize": {
            "type": "dimension",
            "value": 16
          },
          "textDecoration": {
            "type": "string",
            "value": "none"
          },
          "fontFamily": {
            "type": "string",
            "value": "Source Sans Pro"
          },
          "fontWeight": {
            "type": "number",
            "value": 700
          },
          "fontStyle": {
            "type": "string",
            "value": "normal"
          },
          "fontStretch": {
            "type": "string",
            "value": "normal"
          },
          "letterSpacing": {
            "type": "dimension",
            "value": 0
          },
          "lineHeight": {
            "type": "dimension",
            "value": 22
          },
          "paragraphIndent": {
            "type": "dimension",
            "value": 0
          },
          "paragraphSpacing": {
            "type": "dimension",
            "value": 0
          },
          "textCase": {
            "type": "string",
            "value": "none"
          }
        },
        "medium regular": {
          "fontSize": {
            "type": "dimension",
            "value": 16
          },
          "textDecoration": {
            "type": "string",
            "value": "none"
          },
          "fontFamily": {
            "type": "string",
            "value": "Source Sans Pro"
          },
          "fontWeight": {
            "type": "number",
            "value": 400
          },
          "fontStyle": {
            "type": "string",
            "value": "normal"
          },
          "fontStretch": {
            "type": "string",
            "value": "normal"
          },
          "letterSpacing": {
            "type": "dimension",
            "value": 0
          },
          "lineHeight": {
            "type": "dimension",
            "value": 22
          },
          "paragraphIndent": {
            "type": "dimension",
            "value": 0
          },
          "paragraphSpacing": {
            "type": "dimension",
            "value": 0
          },
          "textCase": {
            "type": "string",
            "value": "none"
          }
        }
      }
    }
  }
}